README.md
setup.py
swiftype/__init__.py
swiftype/swiftype.py
swiftype/version.py
swiftype.egg-info/PKG-INFO
swiftype.egg-info/SOURCES.txt
swiftype.egg-info/dependency_links.txt
swiftype.egg-info/requires.txt
swiftype.egg-info/top_level.txt
tests/__init__.py
tests/test_swiftype.py