Metadata-Version: 1.1
Name: swiftype
Version: 1.2.1
Summary: Swiftype API Client for Python
Home-page: https://swiftype.com/
Author: Swiftype
Author-email: team@swiftype.com
License: UNKNOWN
Platform: UNKNOWN
Classifier: Intended Audience :: Developers
Classifier: Operating System :: OS Independent
Classifier: Programming Language :: Python
Classifier: Topic :: Software Development :: Libraries :: Python Modules
